exep_tools/__init__.cpython-311-x86_64-linux-gnu.so
exep_tools/__init__.pyi
exep_tools/builder.cpython-311-x86_64-linux-gnu.so
exep_tools/crypto.cpython-311-x86_64-linux-gnu.so
exep_tools/ex.cpython-311-x86_64-linux-gnu.so
exep_tools/exep_click.cpython-311-x86_64-linux-gnu.so
exep_tools/main.cpython-311-x86_64-linux-gnu.so
exep_tools-0.2.10.dist-info/LICENSE
exep_tools-0.2.10.dist-info/METADATA
exep_tools-0.2.10.dist-info/WHEEL
exep_tools-0.2.10.dist-info/entry_points.txt
exep_tools-0.2.10.dist-info/RECORD
