Metadata-Version: 2.1
Name: exep_tools
Version: 0.2.10
Summary: -
Home-page: https://pypi.org/project/exep_tools
Requires-Python: >=3.11,<4.0
Classifier: Programming Language :: Python :: 3
Classifier: Programming Language :: Python :: 3.11
Classifier: Programming Language :: Python :: 3.12
Requires-Dist: ast-grep-py (>=0.37.0,<0.38.0)
Requires-Dist: click (>=8.1.8,<9.0.0)
Requires-Dist: cython (>=3.1.0,<4.0.0)
Requires-Dist: pycryptodome (>=3.22.0,<4.0.0)
Requires-Dist: python-dateutil (>=2.9.0.post0,<3.0.0)
Requires-Dist: python-dotenv (>=1.1.0,<2.0.0)
Requires-Dist: requests (>=2.32.3,<3.0.0)
